Metadata-Version: 2.4
Name: catch-cap
Version: 0.2.2
Summary: Detect and reduce LLM hallucinations with semantic entropy, log-probability analysis, and web grounding
Home-page: https://github.com/adc77/catch-cap.git
Author: axon_dendrite
Author-email: amandogra2016@gmail.com
Classifier: Development Status :: 3 - Alpha
Classifier: Intended Audience :: Developers
Classifier: License :: OSI Approved :: MIT License
Classifier: Operating System :: OS Independent
Classifier: Programming Language :: Python :: 3.9
Classifier: Programming Language :: Python :: 3.10
Classifier: Programming Language :: Python :: 3.11
Classifier: Topic :: Scientific/Engineering :: Artificial Intelligence
Requires-Python: >=3.9
Requires-Dist: openai>=1.0.0
Requires-Dist: google-genai>=0.5.0
Requires-Dist: groq>=0.4.0
Requires-Dist: tavily-python>=0.3.0
Requires-Dist: scikit-learn>=1.0.0
Requires-Dist: numpy>=1.20.0
Requires-Dist: aiohttp>=3.8.0
Requires-Dist: python-dotenv>=0.19.0
Requires-Dist: tenacity>=8.0.0
Requires-Dist: aiolimiter>=1.1.0
Provides-Extra: dev
Requires-Dist: pytest>=7.0.0; extra == "dev"
Requires-Dist: pytest-asyncio>=0.21.0; extra == "dev"
Requires-Dist: black; extra == "dev"
Requires-Dist: flake8; extra == "dev"
Requires-Dist: mypy; extra == "dev"
Dynamic: author
Dynamic: author-email
Dynamic: classifier
Dynamic: description
Dynamic: description-content-type
Dynamic: home-page
Dynamic: provides-extra
Dynamic: requires-dist
Dynamic: requires-python
Dynamic: summary
